Metadata-Version: 2.1
Name: django-slack-oauth
Version: 1.5.0
Summary: Handles OAuth and stores slack token
Home-page: https://github.com/izdi/django-slack-oauth
Author: Sergey Keller
Author-email: izdieu@gmail.com
License: MIT License
Download-URL: https://github.com/izdi/django-slack-oauth/tarball/1.5.0
Platform: UNKNOWN
Requires-Dist: Django (>=1.8)
Requires-Dist: requests
Requires-Dist: jsonfield
